cli_venv-0.0.1.data/scripts/venv
cli_venv-0.0.1.data/scripts/venv.py
cli_venv-0.0.1.data/scripts/venv_pip_recording
cli_venv-0.0.1.dist-info/METADATA
cli_venv-0.0.1.dist-info/RECORD
cli_venv-0.0.1.dist-info/WHEEL
cli_venv-0.0.1.dist-info/top_level.txt
venv/__init__.py
venv/venv.py
