Metadata-Version: 2.1
Name: cli-venv
Version: 0.0.1
Summary: Fast access/manage to virtualenv between different python versions.
Home-page: https://github.com/duckingod/cli_venv
Author: duckingod
Author-email: kingoduck@gmail.com
License: UNKNOWN
Platform: UNKNOWN
Classifier: Programming Language :: Python :: 3
Classifier: License :: OSI Approved :: MIT License
Classifier: Operating System :: OS Independent
Classifier: Environment :: Console
Requires-Dist: argparse
Requires-Dist: virtualenv
